[
  {
    "title": [
      "Терминал",
      "финпродуктов"
    ],
    "linkName": "atm",
    "video": "/assets/videos/Promo-ATM.mp4",
    "caseContent": [
      {
        "type": "mainScreen",
        "content": {
          "title": [
            "Терминал",
            "финпродуктов"
          ],
          "text": "От терминала по&nbsp;приёму монет до&nbsp;киоска финансовых услуг за&nbsp;3&nbsp;месяца",
          "tags": [
            ""
          ],
          "year": "UX-консалтинг, UI-дизайн, Арт-дирекшн © Coincom, 2018 Q2",
          "video": "/assets/videos/Promo-ATM.mp4"
        }
      },
      {
        "type": "video",
        "class": "case__screen_video",
        "content": {
          "video": "/assets/videos/Case-ATM-2.mp4",
          "videoWidth": "600"
        }
      },
      {
        "type": "doubleSide",
        "class": "case__screen_double",
        "content": [
          {
            "type": "texts",
            "class": "case__screen_light",
            "backgroundColor": "white",
            "content": {
              "title": "",
              "text": ""
            }
          },
          {
            "type": "texts",
            "class": "case__screen_light",
            "backgroundColor": "white",
            "content": {
              "title": "Начало и брифинг",
              "text": "На&nbsp;входе были работающие терминалы MVP и&nbsp;прототипы, описывающие функции продукта. Плюс пожелание, что дизайн должен быть дружественным, но&nbsp;в&nbsp;тоже время показывать, что&nbsp;работать с&nbsp;терминалом безопасно."
            }
          }
        ]
      },
      {
        "type": "video",
        "content": {
          "video": "/assets/images/cases/ATM/Proto.mp4",
          "videoWidth": "700",
          "backgroundImage": "/assets/images/cases/ATM/bg.jpg",
          "backgroundSize": "cover"
        }
      },
      {
        "type": "doubleSide",
        "class": "case__screen_double",
        "content": [
          {
            "type": "texts",
            "backgroundColor": "black",
            "content": {
              "title": "",
              "text": ""
            }
          },
          {
            "type": "texts",
            "backgroundColor": "black",
            "content": {
              "title": "Анализ удачных решений",
              "text": "и&nbsp;работа над&nbsp;принципами построения нового интерфейса"
            }
          }
        ]
      },
      {
        "type": "singlePicture",
        "backgroundColor": "#000",
        "content": {
          "image": "/assets/images/cases/ATM/Refs.jpg",
          "imageWidth": "1560"
        }
      },
      {
        "type": "doubleSide",
        "class": "case__screen_double",
        "content": [
          {
            "type": "texts",
            "backgroundColor": "black",
            "content": {
              "title": "",
              "text": ""
            }
          },
          {
            "type": "singlePicture",
            "backgroundColor": "black",
            "content": {
              "image": "/assets/images/cases/ATM/Sch.png",
              "imageWidth": "500"
          }
          }
        ]
      },

      {
        "type": "doubleSide",
        "class": "case__screen_double",
        "content": [
          {
            "type": "texts",
            "backgroundColor": "black",
            "content": {
              "title": "Суть концепции",
              "text": "Мы должны не&nbsp;просто закрыть потребности пользователей, а&nbsp;влюбить их&nbsp;в&nbsp;сам процесс взаимодействия с&nbsp;терминалом. Для&nbsp;этого используем яркие цвета, анимацию, иллюстрации и&nbsp;супер UX."
            }
          },
          {
            "type": "texts",
            "class": "case__screen_light",
            "backgroundColor": "black",
            "content": {
              "title": "",
              "text": ""
            }
          }
        ]
      },
      {
        "type": "video",
        "content": {
          "video": "/assets/videos/Promo-ATM.mp4",
          "videoWidth": "750",
          "backgroundColor": "black"
        }
      },
      {
        "type": "doubleSide",
        "class": "case__screen_double",
        "content": [
          {
            "type": "texts",
            "backgroundColor": "black",
            "content": {
              "title": "Иллюстрации и&nbsp;анимированные инструкции",
              "text": "от&nbsp;иллюстратора <a href='https://www.facebook.com/profile.php?id=100022514774173/' target='_blank'>Ильи Сергеева</a>",
              "backgroundImage": "/assets/images/cases/ATM/bg-ill.jpg",
              "backgroundSize": "cover"
            }
          },
          {
            "type": "singlePicture",
            "backgroundColor": "white",
            "content": {
              "image": "/assets/images/cases/ATM/Gif-ill.gif",
              "imageWidth": "500"
            }
          }
        ]
      },
      {
        "type": "singlePicture",
        "backgroundColor": "white",
        "content": {
          "image": "/assets/images/cases/ATM/Icons.png",
          "imageWidth": "750"
        }
      },
      {
        "type": "doubleSide",
        "class": "case__screen_double",
        "content": [
          {
            "type": "texts",
            "class": "case__screen_light",
            "backgroundColor": "white",
            "content": {
              "title": "Использование иллюстраций в&nbsp;интерфейсе",
              "text": "и&nbsp;другие экраны терминала"
            }
          },
          {
            "type": "texts",
            "backgroundColor": "white",
            "content": {
              "title": "",
              "text": ""
            }
          }
        ]
      },
      {
        "type": "doubleSide",
        "class": "case__screen_double",
        "content": [
          {
            "type": "singlePicture",
            "backgroundColor": "white",
            "content": {
              "image": "/assets/images/cases/ATM/UI-1.jpg",
              "imageWidth": "400"
            }
          },
          {
            "type": "singlePicture",
            "backgroundColor": "white",
            "content": {
              "image": "/assets/images/cases/ATM/UI-2.jpg",
              "imageWidth": "400"
            }
          }
        ]
      },
      {
        "type": "doubleSide",
        "class": "case__screen_double",
        "content": [
          {
            "type": "texts",
            "backgroundColor": "white",
            "content": {
              "title": "",
              "text": ""
            }
          },
          {
            "type": "singlePicture",
            "backgroundColor": "white",
            "content": {
              "image": "/assets/images/cases/ATM/Screen-1.png",
              "imageWidth": "400"
            }
          }
        ]
      },
      {
        "type": "texts",
        "content": {
          "title": "",
          "text": "",
          "backgroundImage": "/assets/images/cases/ATM/Screens.jpg",
          "backgroundSize": "cover"
        }
      },
      {
        "type": "doubleSide",
        "class": "case__screen_double",
        "content": [
          {
            "type": "singlePicture",
            "backgroundColor": "black",
            "content": {
              "image": "/assets/images/cases/ATM/ATM-1.png",
              "imageWidth": "312"
            }
          },
          {
            "type": "singlePicture",
            "backgroundColor": "white",
            "content": {
              "image": "/assets/images/cases/ATM/ATM-2.png",
              "imageWidth": "250"
            }
          }
        ]
      },
      {
        "type": "texts",
        "class": "case__screen_light",
        "backgroundColor": "white",
        "content": {
          "title": "Результат: +10%&nbsp;к&nbsp;конверсии, после запуска нового интерфейса. Окупаемость 100%&nbsp;инвестиций в&nbsp;дизайн&nbsp;—1&nbsp;месяц.",
          "text": "Карта «живых» терминалов <a href='https://coincom.ru/' target='_blank'>на сайте компании</a>."
        }
      },
      {
        "type": "texts",
        "class": "",
        "backgroundColor": "",
        "content": {
          "title": "Результат: +10%&nbsp;к&nbsp;конверсии, после запуска нового интерфейса. Окупаемость 100%&nbsp;инвестиций в&nbsp;дизайн&nbsp;—1&nbsp;месяц.",
          "text": "Карта «живых» терминалов <a href='https://coincom.ru/' target='_blank'>на сайте компании</a>.",
          "centeredText": true
        }
      }
    ]
  },
  {
    "title": [
      "NPS-система",
      "банка ХК"
    ],
    "linkName": "NPS",
    "video": "/assets/videos/Promo-Polza.mp4",
    "caseContent": [
      {
        "type": "mainScreen",
        "content": {
          "title": [
            "NPS-система",
            "Банка ХК"
          ],
          "text": "Лучшая система лояльности 2019&nbsp;г. по&nbsp;версии Frank Banking Reward Award. <br/> UI-Kit интерфейса лёг в&nbsp;основу дизайн-системы всех продуктов Хоум Кредит Банка.",
          "tags": [
            ""
          ],
          "year": "Rethinking CX/UX/UI © Home Credit Bank, 2017, Q4",
          "video": "/assets/videos/Promo-Polza.mp4"
        }
      },
      {
        "type": "video",
        "class": "case__screen_video",
        "content": {
          "video": "/assets/videos/Case-Polza.mp4"
        }
      },
      {
        "type": "doubleSide",
        "class": "case__screen_double",
        "content": [
          {
            "type": "texts",
            "class": "case__screen_light",
            "backgroundColor": "white",
            "content": {
              "title": "",
              "text": ""
            }
          },
          {
            "type": "texts",
            "class": "case__screen_light",
            "backgroundColor": "white",
            "content": {
              "title": "UX-аналитика существующего интерфейса",
              "text": "1. Слишком большой акцент на&nbsp;поиске <br/>2. Баллы&nbsp;— главная информация, а&nbsp;она спрятана внизу экрана <br/>3. Нечитабильный фильтр акций     "
            }
          }
        ]
      },
      {
        "type": "singlePicture",
        "backgroundColor": "#000",
        "content": {
          "image": "/assets/images/cases/Polza/01@2x.png",
          "imageWidth": "832"
        }
      },
      {
        "type": "doubleSide",
        "class": "case__screen_double",
        "content": [
          {
            "type": "texts",
            "class": "case__screen_light",
            "backgroundColor": "white",
            "content": {
              "title": "Новый бизнес-процесс",
              "text": "Сначала оценили возможность реализации нового CX с&nbsp;бизнес-юнитом"
            }
          },
          {
            "type": "singlePicture",
            "backgroundColor": "black",
            "content": {
              "image": "/assets/images/cases/Polza/paper@2x.jpg",
              "imageWidth": "403"
            }
          }
        ]
      },
      {
        "type": "singlePicture",
        "backgroundColor": "white",
        "content": {
          "image": "/assets/images/cases/Polza/03@2x.jpg",
          "backgroundImage": "/assets/images/cases/Polza/04.png",
          "imageWidth": "788",
          "backgroundSize": "100%",
          "backgroundRepeat": "no-repeat",
          "backgroundPosition": "center"
        }
      },
      {
        "type": "doubleSide",
        "class": "case__screen_double",
        "content": [
          {
            "type": "singlePicture",
            "backgroundColor": "#000",
            "content": {
              "image": "/assets/images/cases/Polza/05-1@2x.png",
              "imageWidth": "360"
            }
          },
          {
            "type": "singlePicture",
            "backgroundColor": "white",
            "content": {
              "image": "/assets/images/cases/Polza/05-2@2x.png",
              "imageWidth": "340"
            }
          }
        ]
      },
      {
        "type": "doubleSide",
        "class": "case__screen_double",
        "content": [
          {
            "type": "texts",
            "class": "case__screen_light",
            "backgroundColor": "white",
            "content": {
              "title": "",
              "text": ""
            }
          },
          {
            "type": "texts",
            "class": "case__screen_light",
            "backgroundColor": "white",
            "content": {
              "title": "+12% к просмотру рекламы, за&nbsp;счёт рекомендуемых акций",
              "text": ""
            }
          }
        ]
      },

      {
        "type": "singlePicture",
        "content": {
          "image": "/assets/images/cases/Polza/07@2x.png",
          "imageWidth": "997",
          "backgroundImage": "/assets/images/cases/Polza/06.jpg",
          "backgroundSize": "cover"
        }
      },
      {
        "type": "singlePicture",
        "backgroundColor": "#fff",
        "content": {
          "image": "/assets/images/cases/Polza/08@2x.gif",
          "imageWidth": "520"
        }
      },
      {
        "type": "singlePicture",
        "content": {
          "image": "/assets/images/cases/Polza/09@2x.jpg",
          "imageWidth": "634",
          "backgroundImage": "/assets/images/cases/Polza/09.jpg",
          "backgroundSize": "50%"
        }
      },
      {
        "type": "doubleSide",
        "class": "case__screen_double",
        "content": [
          {
            "type": "texts",
            "class": "case__screen_light",
            "backgroundColor": "white",
            "content": {
              "title": "",
              "text": ""
            }
          },
          {
            "type": "texts",
            "class": "case__screen_light",
            "backgroundColor": "white",
            "content": {
              "title": "Мобильный трафик — 34%",
              "text": ""
            }
          }
        ]
      },
      {
        "type": "singlePicture",
        "backgroundColor": "white",
        "content": {
          "image": "/assets/images/cases/Polza/10@2x.jpg",
          "imageWidth": "941"
        }
      },
      {
        "type": "texts",
        "backgroundColor": "black",
        "content": {
          "title": "Закажите карту и&nbsp;наслаждайтесь действительно высоким cashback'ом и&nbsp;понятным интерфейсом :) ",
          "text": "<a href='http://polza.homecredit.ru/' target='_blank'>polza.homecredit.ru</a> "
        }
      },


      {
        "type": "texts",
        "content": {
          "title": "",
          "text": "Больше работ для&nbsp;Home Credit Bank<br/> собрано на&nbsp;<a href='http://daily.pirogov.design/' target='_blank'>daily.pirogov.design</a>",
          "backgroundImage": "/assets/images/cases/Polza/Daily.jpg",
          "backgroundSize": "cover"
        }
      }
    ]
  },
  {
    "title": [
      "Екатеринбург",
      "в Каннах"
    ],
    "linkName": "Istokskiy",
    "video": "/assets/videos/Promo-Istokskiy.mp4",
    "caseContent": [
      {
        "type": "mainScreen",
        "content": {
          "title": [
            "Екатеринбург",
            "в Каннах"
          ],
          "text": "Промо-сайт ЖК «Истокский», для презентации проекта застройки на&nbsp;крупнейшем мировом конкурсе архитектуры MIPIM Awards",
          "tags": [
            ""
          ],
          "year": "UX, UI, Айдентика © Studio-V, 2015 Q4",
          "video": "/assets/videos/Promo-Istokskiy.mp4"
        }
      },
      {
        "type": "video",
        "class": "case__screen_video",
        "content": {
          "video": "/assets/videos/Case-Istokskiy.mp4",
          "videoWidth": "1024"
        }
      },
      {
        "type": "doubleSide",
        "class": "case__screen_double",
        "content": [
          {
            "type": "texts",
            "class": "case__screen_light",
            "backgroundColor": "white",
            "content": {
              "title": "",
              "text": ""
            }
          },
          {
            "type": "texts",
            "class": "case__screen_light",
            "backgroundColor": "white",
            "content": {
              "title": "УТП для инвесторов",
              "text": "Стилизованное представление данных помогает привлечь внимание к&nbsp;важному, для&nbsp;продаж, информационному блоку."
            }
          }
        ]
      },
      {
        "type": "doubleSide",
        "class": "case__screen_double",
        "content": [
          {
            "type": "singlePicture",
            "backgroundColor": "black",
            "content": {
              "image": "/assets/images/cases/Istokskiy/utp-1.png",
              "imageWidth": "300"
            }
          },
          {
            "type": "singlePicture",
            "backgroundColor": "white",
            "content": {
              "image": "/assets/images/cases/Istokskiy/utp-2.png",
              "imageWidth": "300"
            }
          }
        ]
      },
      {
        "type": "singlePicture",
        "backgroundColor": "#000",
        "content": {
          "image": "/assets/images/cases/Istokskiy/infr.jpg",
          "imageWidth": "753"
        }
      },
      {
        "type": "doubleSide",
        "class": "case__screen_double",
        "content": [
          {
            "type": "singlePicture",
            "backgroundColor": "black",
            "content": {
              "image": "/assets/images/cases/Istokskiy/Icons.png",
              "imageWidth": "450"
            }
          },
          {
            "type": "singlePicture",
            "backgroundColor": "white",
            "content": {
              "image": "/assets/images/cases/Istokskiy/Icon-big.png",
              "imageWidth": "272"
            }
          }
        ]
      },
      {
        "type": "singlePicture",
        "backgroundColor": "white",
        "content": {
          "image": "/assets/images/cases/Istokskiy/03@2x.jpg",
          "imageWidth": "755"
        }
      },
      {
        "type": "doubleSide",
        "class": "case__screen_double",
        "content": [
          {
            "type": "texts",
            "class": "case__screen_light",
            "backgroundColor": "white",
            "content": {
              "title": "",
              "text": ""
            }
          },
          {
            "type": "texts",
            "class": "case__screen_light",
            "backgroundColor": "white",
            "content": {
              "title": "В основу UI сайта легла <a href='http://www.studio-v.ru/folio/istokskiy-logo/' target='_blank'>айдентика</a> жилого комплекса",
              "text": "Её разработал тоже я"
            }
          }
        ]
      },

      {
        "type": "doubleSide",
        "class": "case__screen_double",
        "content": [
          {
            "type": "texts",
            "class": "case__screen_light",
            "backgroundColor": "white",
            "content": {
              "title": "",
              "text": ""
            }
          },
          {
            "type": "singlePicture",
            "backgroundColor": "white",
            "content": {
              "image": "/assets/images/cases/Istokskiy/Logo.png",
              "imageWidth": "300"
          }
          }
        ]
      },

      {
        "type": "singlePicture",
        "backgroundColor": "#F3F8FA",
        "content": {
          "image": "/assets/images/cases/Istokskiy/04@2x.jpg",
          "imageWidth": "915"
        }
      },
      {
        "type": "texts",
        "class": "case__screen_light",
        "backgroundColor": "white",
        "content": {
          "title": "<a href='http://istokskiy.ru/en/' target='_blank'> istokskiy.ru</a>",
          "text": ""
        }
      }
    ]
  },










  {
    "title": [
      "Трансформация",
      "ЖКХ-сектора"
    ],
    "linkName": "Pik",
    "video": "/assets/videos/Promo-PIK.mp4",
    "caseContent": [
      {
        "type": "mainScreen",
        "content": {
          "title": [
            "Трансформация",
            "ЖКХ-сектора"
          ],
          "text": "Задача: повернуть ЖКХ-сектор лицом к&nbsp;жителям. Опираться на&nbsp;опыт внедрения MVP «Личный кабинет». Создать дизайн-стратегию для&nbsp;развития комплексного продукта.",
          "tags": [
            ""
          ],
          "year": "Аналитика, CX/UX/UI, Арт-дирекшн © ПИК-Комфорт, 2019, Q1",
          "video": "/assets/videos/Promo-PIK.mp4"
        }
      },
      {
        "type": "video",
        "class": "case__screen_video",
        "content": {
          "video": "/assets/videos/Case-PIK.mp4",
          "videoWidth": "900"

        }
      },
      {
        "type": "doubleSide",
        "class": "case__screen_double",
        "content": [
          {
            "type": "texts",
            "class": "case__screen_light",
            "backgroundColor": "white",
            "content": {
              "title": "",
              "text": ""
            }
          },
          {
            "type": "texts",
            "class": "case__screen_light",
            "backgroundColor": "white",
            "content": {
              "title": "Шаг 1",
              "text": "Research предметной области и&nbsp;конкурентной среды, составление матрицы плюсов и&nbsp;минусов конкурентных решений и&nbsp;прорисовка архитекруты будущего приложения"
            }
          }
        ]
      },
      {
        "type": "singlePicture",
        "backgroundColor": "white",
        "content": {
          "image": "/assets/images/cases/Pik/Whimsical.jpg",
          "imageWidth": "700"
        }
      },
      {
        "type": "doubleSide",
        "class": "case__screen_double",
        "content": [
          {
            "type": "texts",
            "class": "case__screen_light",
            "backgroundColor": "white",
            "content": {
              "title": "Бумажные прототипы экранов и&nbsp;утверждение общей UX-концепции приложения",
              "text": "Шаг 2"
            }
          },
          {
            "type": "singlePicture",
            "backgroundColor": "black",
            "content": {
              "image": "/assets/images/cases/Pik/Pic-1.jpg",
              "imageWidth": "400"
            }
          }
        ]
      },
      {
        "type": "doubleSide",
        "class": "case__screen_double",
        "content": [
          {
            "type": "texts",
            "backgroundColor": "black",
            "content": {
              "title": "Wireframes",
              "text": "Шаг 3"
            }
          },
          {
            "type": "texts",
            "class": "case__screen_light",
            "backgroundColor": "black",
            "content": {
              "title": "",
              "text": ""
            }
          }
        ]
      },
      {
        "type": "singlePicture",
        "backgroundColor": "black",
        "content": {
          "image": "/assets/images/cases/Pik/Wireframes.png",
          "imageWidth": "1000"
        }
      },
      {
        "type": "doubleSide",
        "class": "case__screen_double",
        "content": [
          {
            "type": "texts",
            "class": "case__screen_light",
            "backgroundColor": "white",
            "content": {
              "title": "",
              "text": ""
            }
          },
          {
            "type": "texts",
            "class": "case__screen_light",
            "backgroundColor": "white",
            "content": {
              "title": "Draft visual concept",
              "text": "Шаг 4"
            }
          }
        ]
      },
      {
        "type": "singlePicture",
        "backgroundColor": "white",
        "content": {
          "image": "/assets/images/cases/Pik/Draft.jpg",
          "imageWidth": "1000"
        }
      },
      {
        "type": "doubleSide",
        "class": "case__screen_double",
        "content": [
          {
            "type": "singlePicture",
            "backgroundColor": "white",
            "content": {
              "image": "/assets/images/cases/Pik/Variants.gif",
              "imageWidth": "65"
            }
          },
          {
            "type": "texts",
            "backgroundColor": "white",
            "content": {
              "title": "",
              "text": ""
            }
          }
        ]
      },
      {
        "type": "doubleSide",
        "class": "case__screen_double",
        "content": [
          {
            "type": "texts",
            "class": "case__screen_light",
            "backgroundColor": "white",
            "content": {
              "title": "",
              "text": ""
            }
          },
          {
            "type": "texts",
            "class": "case__screen_light",
            "backgroundColor": "white",
            "content": {
              "title": "Итоговый дизайн",
              "text": "Первоначальная концепция показала вектор визуального дизайна приложения. После обсуждения концепции были проработанны все&nbsp;нюансы. Вот, что&nbsp;получилось в&nbsp;итоге…"
            }
          }
        ]
      },
      {
        "type": "texts",
        "content": {
          "title": "",
          "text": "",
          "backgroundImage": "/assets/images/cases/Pik/Mockup.png",
          "backgroundSize": "cover"
        }
      },
      {
        "type": "doubleSide",
        "class": "case__screen_double",
        "content": [
          {
            "type": "singlePicture",
            "backgroundColor": "white",
            "content": {
              "image": "/assets/images/cases/Pik/Dash-i.png",
              "imageWidth": "300"
            }
          },
          {
            "type": "singlePicture",
            "backgroundColor": "white",
            "content": {
              "image": "/assets/images/cases/Pik/Dash-a.png",
              "imageWidth": "300"
            }
          }
        ]
      },
      {
        "type": "doubleSide",
        "class": "case__screen_double",
        "content": [
          {
            "type": "texts",
            "class": "case__screen_light",
            "backgroundColor": "white",
            "content": {
              "title": "Оплата",
              "text": "Квитанции, по&nbsp;которым понятно за&nbsp;что&nbsp;платишь"
            }
          },
          {
            "type": "singlePicture",
            "backgroundColor": "black",
            "content": {
              "image": "/assets/images/cases/Pik/Inv.gif",
              "imageWidth": "200"
            }
          }
        ]
      },
      {
        "type": "doubleSide",
        "class": "case__screen_double",
        "content": [
          {
            "type": "singlePicture",
            "backgroundColor": "#4485EB",
            "content": {
              "image": "/assets/images/cases/Pik/Paid.png",
              "imageWidth": "350"
            }
          },
          {
            "type": "singlePicture",
            "backgroundColor": "white",
            "content": {
              "image": "/assets/images/cases/Pik/Lime.gif",
              "imageWidth": "275"
            }
          }
        ]
      },
      {
        "type": "doubleSide",
        "class": "case__screen_double",
        "content": [
          {
            "type": "texts",
            "class": "case__screen_light",
            "backgroundColor": "white",
            "content": {
              "title": "",
              "text": ""
            }
          },
          {
            "type": "texts",
            "class": "case__screen_light",
            "backgroundColor": "white",
            "content": {
              "title": "Показания сётчиков",
              "text": "и цветовая идентификация типа прибора учёта"
            }
          }
        ]
      },
      {
        "type": "doubleSide",
        "class": "case__screen_double",
        "content": [
          {
            "type": "singlePicture",
            "backgroundColor": "white",
            "content": {
              "image": "/assets/images/cases/Pik/C.gif",
              "imageWidth": "350"
            }
          },
          {
            "type": "singlePicture",
            "backgroundColor": "white",
            "content": {
              "image": "/assets/images/cases/Pik/Colors.png",
              "imageWidth": "235"
            }
          }
        ]
      },
      {
        "type": "singlePicture",
        "backgroundColor": "white",
        "content": {
          "image": "/assets/images/cases/Pik/i-a.png",
          "imageWidth": "146"
        }
      },
      {
        "type": "doubleSide",
        "class": "case__screen_double",
        "content": [
          {
            "type": "texts",
            "class": "case__screen_light",
            "backgroundColor": "white",
            "content": {
              "title": "",
              "text": ""
            }
          },
          {
            "type": "texts",
            "class": "case__screen_light",
            "backgroundColor": "white",
            "content": {
              "title": "Платформенные отличия и&nbsp;адаптация дизайна",
              "text": ""
            }
          }
        ]
      },
      {
        "type": "singlePicture",
        "backgroundColor": "black",
        "content": {
          "image": "/assets/images/cases/Pik/Girl.png",
          "imageWidth": "1100"
        }
      },
      {
        "type": "doubleSide",
        "class": "case__screen_double",
        "content": [
          {
            "type": "texts",
            "backgroundColor": "black",
            "content": {
              "title": "Морфинг экранов оплаты",
              "text": ""
            }
          },
          {
            "type": "texts",
            "class": "case__screen_light",
            "backgroundColor": "black",
            "content": {
              "title": "",
              "text": ""
            }
          }
        ]
      },
      {
        "type": "doubleSide",
        "class": "case__screen_double",
        "content": [
          {
            "type": "singlePicture",
            "backgroundColor": "black",
            "content": {
              "image": "/assets/images/cases/Pik/InvoiceOpen-iOS.gif",
              "imageWidth": "200"
            }
          },
          {
            "type": "singlePicture",
            "backgroundColor": "black",
            "content": {
              "image": "/assets/images/cases/Pik/InvoiceOpen-Android.gif",
              "imageWidth": "185"
            }
          }
        ]
      },
      {
        "type": "doubleSide",
        "class": "case__screen_double",
        "content": [
          {
            "type": "singlePicture",
            "backgroundColor": "black",
            "content": {
              "image": "/assets/images/cases/Pik/Ipu-i.png",
              "imageWidth": "150"
            }
          },
          {
            "type": "singlePicture",
            "backgroundColor": "white",
            "content": {
              "image": "/assets/images/cases/Pik/Ipu-a.png",
              "imageWidth": "150"
            }
          }
        ]
      },
      {
        "type": "doubleSide",
        "class": "case__screen_double",
        "content": [
          {
            "type": "texts",
            "class": "case__screen_light",
            "backgroundColor": "white",
            "content": {
              "title": "",
              "text": ""
            }
          },
          {
            "type": "texts",
            "class": "case__screen_light",
            "backgroundColor": "white",
            "content": {
              "title": "Иконографика",
              "text": ""
            }
          }
        ]
      },
      {
        "type": "singlePicture",
        "backgroundColor": "white",
        "content": {
          "image": "/assets/images/cases/Pik/Icons.jpg",
          "imageWidth": "550"
        }
      },
      {
        "type": "doubleSide",
        "class": "case__screen_double",
        "content": [
          {
            "type": "texts",
            "content": {
              "title":" ",
              "text": " ",
              "backgroundImage": "/assets/images/cases/Pik/Map.jpg",
              "backgroundSize": "cover"
            }
          },
          {
            "type": "texts",
            "class": "case__screen_light",
            "backgroundColor": "white",
            "content": {
              "title": "Спецификации разработки",
              "text": "— Логика переходов между экранами; <br/>— описания анимаций и&nbsp;ключевых кейсов; <br/>— гайды верстки интерфейса; <br/>— карта пуш-уведомлений."
            }
          }
        ]
      },
      {
        "type": "doubleSide",
        "class": "case__screen_double",
        "content": [
          {
            "type": "singlePicture",
            "backgroundColor": "white",
            "content": {
              "image": "/assets/images/cases/Pik/Splash.gif",
              "imageWidth": "253"
            }
          },
          {
            "type": "singlePicture",
            "backgroundColor": "black",
            "content": {
              "image": "/assets/images/cases/Pik/Splash-s.png",
              "imageWidth": "500"
            }
          }
        ]
      },
      {
        "type": "singlePicture",
        "backgroundColor": "black",
        "content": {
          "image": "/assets/images/cases/Pik/Timeline.png",
          "imageWidth": "700"
        }
      },
      {
        "type": "doubleSide",
        "class": "case__screen_double",
        "content": [
          {
            "type": "texts",
            "class": "case__screen_light",
            "backgroundColor": "white",
            "content": {
              "title": "Карта Push-уведомлений",
              "text": "Продумываем о&nbsp;чём, когда, кого и&nbsp;как&nbsp;будем уведомлять"
            }
          },
          {
            "type": "texts",
            "backgroundColor": "black",
            "content": {
              "title":" ",
              "text": " ",
              "backgroundImage": "/assets/images/cases/Pik/Push.jpg",
              "backgroundSize": "cover"
            }
          }
        ]
      },
      {
        "type": "singlePicture",
        "backgroundColor": "black",
        "content": {
          "image": "/assets/images/cases/Pik/Store.jpg",
          "imageWidth": "740"
        }
      },
      {
        "type": "texts",
        "class": "case__screen_light",
        "backgroundColor": "white",
        "content": {
          "title": "После релиза приложения с&nbsp;новым дизайном оценка в&nbsp;сторах изменились с&nbsp;2,3 до&nbsp;4,8",
          "text": "Посмотреть видео «живого» приложения — <a href='https://vimeo.com/381635357' target='_blank'>vimeo.com/381635357</a>. <br/>Установить приложение: <a href='https://itunes.apple.com/ru/app/%D0%BF%D0%B8%D0%BA-%D0%BA%D0%BE%D0%BC%D1%84%D0%BE%D1%80%D1%82-%D0%BC%D0%BE%D0%B9-%D0%BA%D0%B0%D0%B1%D0%B8%D0%BD%D0%B5%D1%82/id1425791360' target='_blank'>App&nbsp;Store</a>, <a href='https://play.google.com/store/apps/details?id=apiqa.ru.residentcabinetandroid' target='_blank'>Google&nbsp;Play.</a>"
        }
      },
      {
        "type": "doubleSide",
        "class": "case__screen_double",
        "content": [
          {
            "type": "texts",
            "backgroundColor": "white",
            "content": {
              "title":" ",
              "text": " "
            }
          },
          {
            "type": "singlePicture",
            "backgroundColor": "white",
            "content": {
              "image": "/assets/images/cases/Pik/Stars.png",
              "imageWidth": "263"
            }
          }
        ]
      }
    ]
  }

]
